<?xml version="1.0"?>
<!DOCTYPE hibernate-mapping PUBLIC "-//Hibernate/Hibernate Mapping DTD 3.0//EN"
"http://www.hibernate.org/dtd/hibernate-mapping-3.0.dtd">
<!-- Generated 4 ??? 2013 5:28:21 ?? by Hibernate Tools 3.6.0 -->
<hibernate-mapping>
    <class name="mynightout.entity.Nightclub" table="nightclub" catalog="mynightout">
        <id name="clubId" type="java.lang.Integer">
            <column name="Club_id" />
            <generator class="identity" />
        </id>
        <property name="clubName" type="string">
            <column name="Club_name" length="30" not-null="true" />
        </property>
        <property name="clubPassword" type="string">
            <column name="Club_password" length="15" not-null="true" />
        </property>
        <property name="address" type="string">
            <column name="Address" length="50" not-null="true" />
        </property>
        <property name="emailAddress" type="string">
            <column name="Email_address" length="60" not-null="true" />
        </property>
        <property name="seatNumber" type="int">
            <column name="Seat_number" not-null="true" />
        </property>
        <property name="telephoneNum" type="string">
            <column name="Telephone_num" length="10" not-null="true" />
        </property>
        <property name="categoryId" type="string">
            <column name="Category_id" length="1" not-null="true" />
        </property>
        <property name="clubImage" type="string">
            <column name="Club_image" length="200" not-null="true" />
        </property>
        <property name="closedFrom" type="date">
            <column name="Closed_from" length="10" not-null="true" />
        </property>
        <property name="closedThrough" type="date">
            <column name="Closed_through" length="10" not-null="true" />
        </property>
        <property name="daysClosed" type="string">
            <column name="Days_closed" length="13" not-null="true" />
        </property>
    </class>
</hibernate-mapping>
